py_swagger_ui/__init__.py
py_swagger_ui/vendor/swagger-ui-4.15.5/favicon-16x16.png
py_swagger_ui/vendor/swagger-ui-4.15.5/favicon-32x32.png
py_swagger_ui/vendor/swagger-ui-4.15.5/index.css
py_swagger_ui/vendor/swagger-ui-4.15.5/index.html
py_swagger_ui/vendor/swagger-ui-4.15.5/index.j2
py_swagger_ui/vendor/swagger-ui-4.15.5/oauth2-redirect.html
py_swagger_ui/vendor/swagger-ui-4.15.5/swagger-initializer.js
py_swagger_ui/vendor/swagger-ui-4.15.5/swagger-ui-bundle.js
py_swagger_ui/vendor/swagger-ui-4.15.5/swagger-ui-bundle.js.map
py_swagger_ui/vendor/swagger-ui-4.15.5/swagger-ui-es-bundle-core.js
py_swagger_ui/vendor/swagger-ui-4.15.5/swagger-ui-es-bundle-core.js.map
py_swagger_ui/vendor/swagger-ui-4.15.5/swagger-ui-es-bundle.js
py_swagger_ui/vendor/swagger-ui-4.15.5/swagger-ui-es-bundle.js.map
py_swagger_ui/vendor/swagger-ui-4.15.5/swagger-ui-standalone-preset.js
py_swagger_ui/vendor/swagger-ui-4.15.5/swagger-ui-standalone-preset.js.map
py_swagger_ui/vendor/swagger-ui-4.15.5/swagger-ui.css
py_swagger_ui/vendor/swagger-ui-4.15.5/swagger-ui.css.map
py_swagger_ui/vendor/swagger-ui-4.15.5/swagger-ui.js
py_swagger_ui/vendor/swagger-ui-4.15.5/swagger-ui.js.map
py_swagger_ui/vendor/swagger-ui-4.4.0/favicon-16x16.png
py_swagger_ui/vendor/swagger-ui-4.4.0/favicon-32x32.png
py_swagger_ui/vendor/swagger-ui-4.4.0/index.html
py_swagger_ui/vendor/swagger-ui-4.4.0/index.j2
py_swagger_ui/vendor/swagger-ui-4.4.0/oauth2-redirect.html
py_swagger_ui/vendor/swagger-ui-4.4.0/swagger-ui-bundle.js
py_swagger_ui/vendor/swagger-ui-4.4.0/swagger-ui-bundle.js.map
py_swagger_ui/vendor/swagger-ui-4.4.0/swagger-ui-es-bundle-core.js
py_swagger_ui/vendor/swagger-ui-4.4.0/swagger-ui-es-bundle-core.js.map
py_swagger_ui/vendor/swagger-ui-4.4.0/swagger-ui-es-bundle.js
py_swagger_ui/vendor/swagger-ui-4.4.0/swagger-ui-es-bundle.js.map
py_swagger_ui/vendor/swagger-ui-4.4.0/swagger-ui-standalone-preset.js
py_swagger_ui/vendor/swagger-ui-4.4.0/swagger-ui-standalone-preset.js.map
py_swagger_ui-1.0.0.dist-info/METADATA
py_swagger_ui-1.0.0.dist-info/LICENSE
py_swagger_ui-1.0.0.dist-info/WHEEL
py_swagger_ui-1.0.0.dist-info/RECORD
